file_structure_compressor/__init__.py
file_structure_compressor/cli.py
file_structure_compressor-0.1.0.dist-info/licenses/LICENSE
file_structure_compressor-0.1.0.dist-info/METADATA
file_structure_compressor-0.1.0.dist-info/WHEEL
file_structure_compressor-0.1.0.dist-info/entry_points.txt
file_structure_compressor-0.1.0.dist-info/top_level.txt
file_structure_compressor-0.1.0.dist-info/RECORD
